{
      "teamHome": "Grêmio",
      "teamVisiting": "Bahia",
      "EventTime": "19:15",
      "EventDate": "Qua, 10 de julho",
      "info": "Copa do Brasil: Quartas de final: 1-2",
      "teamHomeImg": "https://ssl.gstatic.com/onebox/media/sports/logos/Ku-73v_TW9kpex-IEGb0ZA_96x96.png",
      "teamVisitingImg": "https://ssl.gstatic.com/onebox/media/sports/logos/nIdbR6qIUDyZUBO9vojSPw_96x96.png",
      "link": "https://sportzonline.co/channels/bra/br1.php"
},
{
      "teamHome": "Athletico-PR",
      "teamVisiting": "Flamengo",
      "EventTime": "21:30",
      "EventDate": "Qua, 10 de julho",
      "info": "Copa do Brasil: Quartas de final: 1-2",
      "teamHomeImg": "https://ssl.gstatic.com/onebox/media/sports/logos/wDMLzBXmGU4qz1lXUnBQvQ_96x96.png",
      "teamVisitingImg": "https://ssl.gstatic.com/onebox/media/sports/logos/orE554NToSkH6nuwofe7Yg_96x96.png",
      "link": "https://sportzonline.co/channels/bra/br1.php"
},
{
      "teamHome": "Palmeiras",
      "teamVisiting": "Internacional",
      "EventTime": "21:30",
      "EventDate": "Qua, 10 de julho",
      "info": "Copa do Brasil: Quartas de final: 1-2",
      "teamHomeImg": "https://ssl.gstatic.com/onebox/media/sports/logos/7spurne-xDt2p6C0imYYNA_96x96.png",
      "teamVisitingImg": "https://ssl.gstatic.com/onebox/media/sports/logos/OWVFKuHrQuf4q2Wk0hEmSA_96x96.png",
      "link": "https://sportzonline.co/channels/bra/br2.php"
  }
};
